odoo/addons/stock_picking_purchase_propagate/README.rst
odoo/addons/stock_picking_purchase_propagate/__init__.py
odoo/addons/stock_picking_purchase_propagate/__manifest__.py
odoo/addons/stock_picking_purchase_propagate/i18n/stock_picking_purchase_propagate.pot
odoo/addons/stock_picking_purchase_propagate/models/__init__.py
odoo/addons/stock_picking_purchase_propagate/models/purchase.py
odoo/addons/stock_picking_purchase_propagate/models/stock_move.py
odoo/addons/stock_picking_purchase_propagate/static/description/icon.png
odoo/addons/stock_picking_purchase_propagate/tests/__init__.py
odoo/addons/stock_picking_purchase_propagate/tests/test_po_propagate.py
odoo11_addon_stock_picking_purchase_propagate-11.0.1.0.0.99.dev14.dist-info/METADATA
odoo11_addon_stock_picking_purchase_propagate-11.0.1.0.0.99.dev14.dist-info/RECORD
odoo11_addon_stock_picking_purchase_propagate-11.0.1.0.0.99.dev14.dist-info/WHEEL
odoo11_addon_stock_picking_purchase_propagate-11.0.1.0.0.99.dev14.dist-info/top_level.txt
