Metadata-Version: 2.1
Name: odoo11-addon-stock-picking-purchase-propagate
Version: 11.0.1.0.0.99.dev14
Summary: Propagate procurement group and quantity from purchase order
Home-page: https://github.com/OCA/stock-logistics-workflow
Author: Camptocamp, Odoo Community Association (OCA)
Author-email: support@odoo-community.org
License: AGPL-3
Platform: UNKNOWN
Classifier: Programming Language :: Python
Classifier: Framework :: Odoo
Classifier: License :: OSI Approved :: GNU Affero General Public License v3
Requires-Python: >=2.7, !=3.0.*, !=3.1.*, !=3.2.*, !=3.3.*, !=3.4.*
Requires-Dist: odoo11-addon-purchase-line-procurement-group
Requires-Dist: odoo (<11.1dev,>=11.0a)
